Metadata-Version: 1.1
Name: godaddyip
Version: 0.1.2
Summary: Maintains A and CNAME records matching current ip in Godaddy.
Home-page: https://github.com/ibizaman/godaddyip
Author: Pierre Penninckx
Author-email: ibizapeanut@gmail.com
License: GPLv3
Download-URL: https://github.com/ibizaman/godaddyip/archive/0.1.2.tar.gz
Keywords: godaddy,dyndns
Platform: UNKNOWN
